rfwc/__init__.py
rfwc/obscure_data.py
rfwc/red_flagger.py
rfwc/utils.py
rfwc/data/toxic_keywords_b16.txt
rfwc-0.1.2.dist-info/licenses/LICENSE
rfwc-0.1.2.dist-info/WHEEL
rfwc-0.1.2.dist-info/METADATA
rfwc-0.1.2.dist-info/RECORD
