Metadata-Version: 2.4
Name: rfwc
Version: 0.1.2
Summary: A software that uses an curated open-source keyword list to detect hate.
Author-email: Daniel Yakubov <danielyak98@gmail.com>, Ziggy Cross <ziggycross@me.com>, Sara Davis <sara.rai.davis@gmail.com>
Requires-Python: >=3.9
License-Expression: MIT
Classifier: Programming Language :: Python :: 3
Classifier: Operating System :: OS Independent
License-File: LICENSE
Project-URL: Homepage, https://github.com/DanielYakubov/abuse-keywords
Project-URL: Issues, https://github.com/DanielYakubov/abuse-keywords/issues
